torchxai/__init__.py
torchxai/utils.py
torchxai/cka/__init__.py
torchxai/cka/cka.py
torchxai/erf/__init__.py
torchxai/erf/erf.py
torchxai/landscape/__init__.py
torchxai/landscape/landscape.py
torchxai/tsne/__init__.py
torchxai/tsne/tsne.py
torchxai-0.0.4.dist-info/LICENSE
torchxai-0.0.4.dist-info/METADATA
torchxai-0.0.4.dist-info/WHEEL
torchxai-0.0.4.dist-info/top_level.txt
torchxai-0.0.4.dist-info/RECORD
