Metadata-Version: 2.1
Name: torchxai
Version: 0.0.4
Summary: Visualzation methods that help developers to realize the deep network
Home-page: https://github.com/jimmylin0979/torchxai
Author: jimmylin0979
Author-email: jimmylin0979@gmail.com
Keywords: deep learning,torch,explainable,visualization
Classifier: Programming Language :: Python :: 3
Classifier: License :: OSI Approved :: MIT License
Classifier: Operating System :: OS Independent
Requires-Python: >=3
License-File: LICENSE
Requires-Dist: setuptools
Requires-Dist: numpy (>=1.23.4)
Requires-Dist: seaborn (>=0.12.2)
Requires-Dist: torch (>=1.13.1)
Requires-Dist: torchvision
Requires-Dist: tqdm (>=4.63.0)
Requires-Dist: matplotlib (>=3.6.2)
Requires-Dist: seaborn
